dlnpyutils/MagellanicStream.py
dlnpyutils/__init__.py
dlnpyutils/astro.py
dlnpyutils/bindata.py
dlnpyutils/coords.py
dlnpyutils/db.py
dlnpyutils/decompose.py
dlnpyutils/distribution.py
dlnpyutils/email.py
dlnpyutils/galaxy_model.py
dlnpyutils/gaps.py
dlnpyutils/job_daemon.py
dlnpyutils/ladfit.py
dlnpyutils/least_squares.py
dlnpyutils/lsqr.py
dlnpyutils/minpack.py
dlnpyutils/mmm.py
dlnpyutils/mpcommon.py
dlnpyutils/nbody.py
dlnpyutils/plotting.py
dlnpyutils/resample.py
dlnpyutils/robust.py
dlnpyutils/scipy_lib_array_api.py
dlnpyutils/scipy_lib_util.py
dlnpyutils/slurm.py
dlnpyutils/spec.py
dlnpyutils/thumbnail.py
dlnpyutils/trf.py
dlnpyutils/utils.py
dlnpyutils-1.0.83.data/scripts/bump
dlnpyutils-1.0.83.data/scripts/job_daemon
dlnpyutils-1.0.83.data/scripts/topypi
dlnpyutils-1.0.83.dist-info/licenses/LICENSE
dlnpyutils-1.0.83.dist-info/METADATA
dlnpyutils-1.0.83.dist-info/WHEEL
dlnpyutils-1.0.83.dist-info/top_level.txt
dlnpyutils-1.0.83.dist-info/RECORD
