Metadata-Version: 2.4
Name: dlnpyutils
Version: 1.0.83
Summary: A package of useful python utility functions
Home-page: https://github.com/dnidever/dlnpyutils
Author: David Nidever
Author-email: David Nidever <dnidever@montana.edu>
Maintainer-email: David Nidever <dnidever@montana.edu>
License:                     GNU GENERAL PUBLIC LICENSE
Project-URL: Documentation, https://dlnpyutils.readthedocs.org
Project-URL: Repository, https://github.com/dnidever/dlnpyutils
Keywords: utility,astronomy
Classifier: Development Status :: 3 - Alpha
Classifier: License :: OSI Approved :: MIT License
Classifier: Programming Language :: Python
Requires-Python: >=3.9
License-File: LICENSE
Requires-Dist: scipy
Requires-Dist: numpy
Requires-Dist: astropy
Provides-Extra: gui
Requires-Dist: PyQt5; extra == "gui"
Provides-Extra: cli
Requires-Dist: rich; extra == "cli"
Requires-Dist: click; extra == "cli"
Dynamic: author
Dynamic: home-page
Dynamic: license-file
